siam/__init__.py
siam/cracker.py
siam/siam.py
siamwifi-1.0.1.dist-info/LICENSE
siamwifi-1.0.1.dist-info/METADATA
siamwifi-1.0.1.dist-info/WHEEL
siamwifi-1.0.1.dist-info/entry_points.txt
siamwifi-1.0.1.dist-info/top_level.txt
siamwifi-1.0.1.dist-info/RECORD
